LICENSE
MANIFEST.in
README.md
setup.py
./README.md
Finance_Hermes.egg-info/PKG-INFO
Finance_Hermes.egg-info/SOURCES.txt
Finance_Hermes.egg-info/dependency_links.txt
Finance_Hermes.egg-info/requires.txt
Finance_Hermes.egg-info/top_level.txt
hermes/__init__.py
hermes/factors/__init__.py
hermes/factors/base.c
hermes/factors/base.pyx
hermes/factors/alphax/__init__.py
hermes/factors/alphax/factor_alpha101.py
hermes/factors/alphax/factor_alpha191.py
hermes/factors/alphax/core/__init__.py
hermes/factors/alphax/core/alpha101.py
hermes/factors/alphax/core/alpha191.py
hermes/factors/experimental/__init__.py
hermes/factors/experimental/factor_momchain.py
hermes/factors/experimental/core/__init__.py
hermes/factors/experimental/core/dissection.py
hermes/factors/experimental/core/momchain.py
hermes/factors/forecast/__init__.py
hermes/factors/forecast/factor_consensus.c
hermes/factors/forecast/factor_consensus.pyx
hermes/factors/fundamentals/__init__.py
hermes/factors/fundamentals/factor_basis.py
hermes/factors/fundamentals/factor_earning.c
hermes/factors/fundamentals/factor_earning.pyx
hermes/factors/fundamentals/factor_growth.c
hermes/factors/fundamentals/factor_growth.pyx
hermes/factors/fundamentals/factor_size.c
hermes/factors/fundamentals/factor_size.pyx
hermes/factors/fundamentals/factor_value.c
hermes/factors/fundamentals/factor_value.pyx
hermes/factors/fundamentals/core/__init__.py
hermes/factors/fundamentals/core/basis.py
hermes/factors/hfreduction/__init__.py
hermes/factors/hfreduction/factor_moneyflow.c
hermes/factors/hfreduction/factor_moneyflow.pyx
hermes/factors/macroeconmic/__init__.py
hermes/factors/other/__init__.py
hermes/factors/other/factor_com.c
hermes/factors/other/factor_com.pyx
hermes/factors/technical/__init__.py
hermes/factors/technical/factor_formula_stock.c
hermes/factors/technical/factor_formula_stock.pyx
hermes/factors/technical/factor_liquidity_stock.c
hermes/factors/technical/factor_liquidity_stock.pyx
hermes/factors/technical/factor_maturity.py
hermes/factors/technical/factor_momentum.py
hermes/factors/technical/factor_momentum_stock.c
hermes/factors/technical/factor_momentum_stock.pyx
hermes/factors/technical/factor_overlap.py
