Metadata-Version: 2.1
Name: Finance-Hermes
Version: 0.4.1
Summary: FinHermes 0.4.1
Home-page: https://github.com/flaght
Author: flaght
Author-email: flaght@gmail.com
License-File: LICENSE
